lash/__init__.py
lash/app_math.py
lash/executor.py
lash/file_handler.py
lash/image_handler.py
lash/webTools.py
lash/Exportables/__init__.py
lash/Exportables/config.py
lash/Exportables/fileTools.py
lash/Exportables/ikeyboard.py
lash/Exportables/imageTools.py
lash/Exportables/imouse.py
lash/ExtraTools/__init__.py
lash/ExtraTools/bonus.py
lash/ExtraTools/sched_manager.py
lash/ExtraTools/spy.py
lash/ExtraTools/Devices/__init__.py
lash/ExtraTools/Devices/keyboard.py
lash/ExtraTools/Devices/tmouse.py
lash-1.2.1.dist-info/LICENSE
lash-1.2.1.dist-info/METADATA
lash-1.2.1.dist-info/WHEEL
lash-1.2.1.dist-info/top_level.txt
lash-1.2.1.dist-info/zip-safe
lash-1.2.1.dist-info/RECORD
