Metadata-Version: 2.1
Name: lash
Version: 1.2.1
Summary: Cli tools package to desktop
Home-page: https://github.com/KevBoyz/Lash
Author: Kevin Emmanuel
Author-email: kevboyz@pm.me
License: GNU GPLv3
Keywords: toll tolls toolkit keylogger auto-clicker zip organize files file-handler os random schedule spy spyware
Platform: UNKNOWN
Classifier: Development Status :: 5 - Production/Stable
Classifier: Programming Language :: Python :: 3.10
Classifier: Intended Audience :: End Users/Desktop
Classifier: Natural Language :: English
Classifier: Operating System :: OS Independent
Classifier: Topic :: Desktop Environment :: File Managers
Classifier: Topic :: Software Development :: Build Tools
Classifier: Topic :: System :: Archiving :: Compression
Classifier: Topic :: System :: Monitoring
Classifier: Topic :: Utilities
Classifier: License :: OSI Approved :: GNU General Public License v3 or later (GPLv3+)
Requires-Python: >=3.8
Requires-Dist: click (~=8.0.1)
Requires-Dist: pynput (~=1.7.3)
Requires-Dist: keyboard (~=0.13.5)
Requires-Dist: schedule (~=1.1.0)
Requires-Dist: setuptools (~=56.0.0)
Requires-Dist: pyaes (~=1.6.1)
Requires-Dist: requests (~=2.26.0)
Requires-Dist: bs4 (~=0.0.1)
Requires-Dist: pillow (~=8.4.0)
Requires-Dist: matplotlib (~=3.5.0)
Requires-Dist: tqdm (~=4.62.3)
